[{"buildOrder":21,"reportUrl":"https://ITFriendly.github.io/playwright_teach/21/","reportName":"Allure Report with history","data":{"duration":177855}},{"buildOrder":21,"reportUrl":"https://ITFriendly.github.io/playwright_teach/21/","reportName":"Allure Report with history","data":{"duration":194950}},{"buildOrder":21,"reportUrl":"https://ITFriendly.github.io/playwright_teach/21/","reportName":"Allure Report with history","data":{"duration":205690}},{"buildOrder":20,"reportUrl":"https://ITFriendly.github.io/playwright_teach/20/","reportName":"Allure Report with history","data":{"duration":51768}},{"buildOrder":19,"reportUrl":"https://ITFriendly.github.io/playwright_teach/19/","reportName":"Allure Report with history","data":{"duration":42635}},{"buildOrder":18,"reportUrl":"https://ITFriendly.github.io/playwright_teach/18/","reportName":"Allure Report with history","data":{"duration":50608}},{"buildOrder":18,"reportUrl":"https://ITFriendly.github.io/playwright_teach/18/","reportName":"Allure Report with history","data":{"duration":88410}},{"buildOrder":17,"reportUrl":"https://ITFriendly.github.io/playwright_teach/17/","reportName":"Allure Report with history","data":{"duration":59931}},{"buildOrder":17,"reportUrl":"https://ITFriendly.github.io/playwright_teach/17/","reportName":"Allure Report with history","data":{"duration":88800}},{"buildOrder":16,"reportUrl":"https://ITFriendly.github.io/playwright_teach/16/","reportName":"Allure Report with history","data":{"duration":37469}},{"buildOrder":15,"reportUrl":"https://ITFriendly.github.io/playwright_teach/15/","reportName":"Allure Report with history","data":{"duration":44266}},{"buildOrder":14,"reportUrl":"https://ITFriendly.github.io/playwright_teach/14/","reportName":"Allure Report with history","data":{"duration":37143}},{"buildOrder":13,"reportUrl":"https://ITFriendly.github.io/playwright_teach/13/","reportName":"Allure Report with history","data":{"duration":42305}},{"buildOrder":12,"reportUrl":"https://ITFriendly.github.io/playwright_teach/12/","reportName":"Allure Report with history","data":{"duration":38070}},{"buildOrder":11,"reportUrl":"https://ITFriendly.github.io/playwright_teach/11/","reportName":"Allure Report with history","data":{"duration":43122}},{"buildOrder":10,"reportUrl":"https://ITFriendly.github.io/playwright_teach/10/","reportName":"Allure Report with history","data":{"duration":48978}},{"buildOrder":9,"reportUrl":"https://ITFriendly.github.io/playwright_teach/9/","reportName":"Allure Report with history","data":{"duration":12993}},{"buildOrder":8,"reportUrl":"https://ITFriendly.github.io/playwright_teach/8/","reportName":"Allure Report with history","data":{"duration":15804}},{"buildOrder":7,"reportUrl":"https://ITFriendly.github.io/playwright_teach/7/","reportName":"Allure Report with history","data":{"duration":10052}},{"buildOrder":6,"reportUrl":"https://ITFriendly.github.io/playwright_teach/6/","reportName":"Allure Report with history","data":{"duration":8737}}]